{
  "account": {
    "account_id": "acct-xiaozhu-edu-xhs",
    "tenant_id": "tenant-xiaozhu",
    "display_name": "小猪 · 教育小红书号",
    "track_id": "education-yowow",
    "platform_id": "xiaohongshu",
    "positioning_id": "expert"
  },
  "board": {
    "picks": [
      {
        "hotspot_id": "hs-20260612-212",
        "recommendation": "strong_pick",
        "forced_flag": false,
        "skip_reason": null,
        "bridge_paths": [
          {
            "path_id": "p1",
            "phenomenon": "暑假临近，屏幕争夺战话题再起：没收、断网、吼叫全失效，家长求规则模板的帖子刷屏。",
            "real_problem": "表面在吵『怎么堵』，暴露的现实是：堵了十年没堵住，因为这从来不是意志力问题，是供给问题——屏幕提供了高质量、即时、无限的内容，而孩子的离屏生活里没有对等的供给。",
            "track_relation": "超然一层看：争夺战的正路不是把屏幕拿走，是把『离屏输入』的质量提上来——孩子需要的不是禁令，是更有意思的去处。",
            "product_value_support": "暑假规则三件套：①规则和孩子一起定（有参与才有遵守）；②屏幕时间绑定『先完成的真实活动』；③家长负责供给——每天一个值得期待的离屏安排，哪怕只是楼下抓虫。",
            "platform_expression": "小红书图文：用『斗争失败实录』开场共情，给暑假三件套。",
            "naturalness_note": "暑期最大公约数痛点，直通主张。"
          },
          {
            "path_id": "p2",
            "phenomenon": "老人带娃管不住屏幕。",
            "real_problem": "隔代规则不一致。",
            "track_relation": "规则一致性比严格更重要。",
            "product_value_support": "全家统一的简单版规则。",
            "platform_expression": "清单。",
            "naturalness_note": "次选。"
          },
          {
            "path_id": "p3",
            "phenomenon": "孩子用屏幕学习边界模糊。",
            "real_problem": "学习和娱乐混在一台设备。",
            "track_relation": "按用途不按时长管理。",
            "product_value_support": "分场景管理法。",
            "platform_expression": "对照表。",
            "naturalness_note": "可用。"
          }
        ],
        "chosen_path_id": "p1",
        "content": {
          "topic": "屏幕争夺战打输十年，是因为方向反了：问题在供给不在禁令",
          "title": "暑假还没开始我先认输？不，今年换打法：不堵了，卷供给📵➡️🌳",
          "body_or_script": "马上暑假，又到全家『屏幕争夺战』开打的季节。没收、断网、吼——去年全试过，三天就破功。\n\n今年我想通了一件事：**这场仗打输，不是孩子意志力差，是我们拿『禁令』在跟『全世界最好玩的内容』竞争**。怎么可能赢？\n\n屏幕的问题从来不是屏幕，是孩子的离屏生活太无聊了。\n\n暑假换打法三件套👇\n1️⃣ 规则一起定：跟孩子谈判出双方都签字的版本——有参与才有遵守。\n2️⃣ 屏幕时间用『真实活动』换：先完成今天的探险/手工/运动，屏幕时间自动解锁。\n3️⃣ 家长负责供给：每天准备一个值得期待的离屏安排——楼下抓虫、菜场砍价、拆旧家电都算。\n\n禁令省事但没用，供给费心但管用。这个暑假试试卷供给💪\n\n你家的屏幕大战打到第几年了？评论区聊聊👇"
        },
        "external_terms_check": true,
        "risk_note": "不指责家长过往做法；三件套要可操作，别写成鸡汤。",
        "track_id": "education-yowow",
        "platform_id": "xiaohongshu",
        "positioning_id": "expert"
      },
      {
        "hotspot_id": "hs-20260612-205",
        "recommendation": "strong_pick",
        "forced_flag": false,
        "skip_reason": null,
        "bridge_paths": [
          {
            "path_id": "p1",
            "phenomenon": "《爸爸当家5》里乐悠主动安抚妹妹、包揽家务，5000 万播放，全网吵『被迫懂事』还是『有责任感』。",
            "real_problem": "表面在吵立场，暴露的现实是：大家分不清两种『懂事』——一种是看大人脸色的牺牲，一种是被真实需要、又有能力接住的担当。前者消耗孩子，后者滋养孩子。",
            "track_relation": "超然一层看：责任感不是教出来的，是『被需要 + 接得住』喂出来的——区别只在任务是真是假、孩子有没有选择权。",
            "product_value_support": "给孩子真实的、大小合适的任务（不是表演性家务），并允许他做不好：这是把『懂事之争』转化为可操作育儿的钥匙。",
            "platform_expression": "小红书图文：用 5000 万播放的片段做引子，给『真任务 vs 假任务』对照清单。",
            "naturalness_note": "综艺样本+普遍争议，桥自然。"
          },
          {
            "path_id": "p2",
            "phenomenon": "二胎家庭围观这段最有感。",
            "real_problem": "老大被默认要让着。",
            "track_relation": "公平感来自规则不是牺牲。",
            "product_value_support": "家庭任务怎么分龄分配。",
            "platform_expression": "清单。",
            "naturalness_note": "次选。"
          },
          {
            "path_id": "p3",
            "phenomenon": "爸爸带娃节目走红。",
            "real_problem": "父亲参与度仍是稀缺。",
            "track_relation": "参与方式比时长重要。",
            "product_value_support": "给爸爸的三个真任务。",
            "platform_expression": "对话体。",
            "naturalness_note": "可用。"
          }
        ],
        "chosen_path_id": "p1",
        "content": {
          "topic": "懂事分两种：一种在消耗孩子，一种在滋养孩子",
          "title": "看完乐悠那段5000万播放的视频，我想说：别急着心疼『懂事』的孩子😢",
          "body_or_script": "《爸爸当家》里乐悠安抚妹妹、抢着做家务那段，播放破 5000 万，评论区吵翻：一半人心疼『被迫懂事』，一半人羡慕『有责任感』。\n\n其实两边吵的不是一件事。懂事分两种👇\n\n❌ 消耗型：看大人脸色、压抑自己需求换表扬——这种越早越伤。\n✅ 滋养型：被真实需要、任务大小合适、做砸了也没关系——这种是能力的种子。\n\n判断方法就一条：**这个任务是真的吗？孩子能说不吗？**\n\n表演给镜头的家务是假任务；妹妹真的在哭、他真的会哄，是真任务。\n\n所以别不让孩子『懂事』，要给他真实的、接得住的、可以拒绝的事做。被需要的感觉，是孩子自信最早的来源💪\n\n你家孩子做过什么让你惊讶的『真任务』？评论区聊聊👇"
        },
        "external_terms_check": true,
        "risk_note": "对节目和孩子保持善意，不评判具体家庭；争议话题，发布前可交博士过一眼。",
        "track_id": "education-yowow",
        "platform_id": "xiaohongshu",
        "positioning_id": "expert"
      },
      {
        "hotspot_id": "hs-20260612-204",
        "recommendation": "strong_pick",
        "forced_flag": false,
        "skip_reason": null,
        "bridge_paths": [
          {
            "path_id": "p1",
            "phenomenon": "高考后 AI 志愿填报工具爆发，3000 所高校的信息量让家长第一次大规模依赖 AI 做人生决策。",
            "real_problem": "表面在围观工具神奇，暴露的现实是：AI 能瞬间给出方案，但『我要什么、我愿意放弃什么』它替代不了——没练过判断的人，只会把决定权拱手让出。",
            "track_relation": "超然一层看：这不是高考家庭的事，是所有孩子的预演——他们这代人每个重大决策旁边都会站着一个 AI，会提问、会设目标、会对方案挑刺的人才是主人。",
            "product_value_support": "从小学就能练『人机协作的决策课』：让孩子用 AI 查资料后必须回答三个问题——它漏了什么？它怎么知道的？你自己怎么选？",
            "platform_expression": "小红书图文：用『AI 三秒出志愿方案』做钩子，落到家庭版三问清单。",
            "naturalness_note": "AI 决策话题直通本账号核心主张，桥零距离。"
          },
          {
            "path_id": "p2",
            "phenomenon": "考试期间各平台禁用涉考功能。",
            "real_problem": "一刀切禁用解决不了能力问题。",
            "track_relation": "会用和会判断是两回事。",
            "product_value_support": "教孩子把 AI 当陪练不当答案机。",
            "platform_expression": "图文对比两种用法。",
            "naturalness_note": "次选。"
          },
          {
            "path_id": "p3",
            "phenomenon": "志愿信息差扩大。",
            "real_problem": "信息多≠判断好。",
            "track_relation": "筛选与建模才是核心。",
            "product_value_support": "三步筛选法。",
            "platform_expression": "清单体。",
            "naturalness_note": "可用。"
          }
        ],
        "chosen_path_id": "p1",
        "content": {
          "topic": "孩子未来每个大决定旁边都站着 AI，谁来当主人",
          "title": "AI 三秒填好志愿那一刻，我反而更确定小学该练什么了🤖",
          "body_or_script": "高考刚结束，AI 志愿填报直接刷屏：3000 所学校、几万个专业，AI 三秒给方案。\n\n很多家长看完很兴奋，我看完后背一紧：方案是它给的，可『我想要什么、我愿意放弃什么』，它一个字都答不了。\n\n这就是孩子这代人的真实处境——未来每个重大决策旁边都站着一个 AI。区别只在：你是提问的主人，还是接受答案的乘客。\n\n从小学就能练的『人机三问』👇\n1️⃣ 它漏了什么？（AI 给完答案，让孩子找一个它没考虑的角度）\n2️⃣ 它怎么知道的？（追问依据，练源头意识）\n3️⃣ 你自己怎么选？（最后一步永远留给人）\n\n工具越强，会提问的人越值钱。这件事，等到高三就晚了💪\n\n你家孩子用 AI 是问答案还是问思路？评论区聊聊👇"
        },
        "external_terms_check": true,
        "risk_note": "不评价具体志愿工具好坏，不制造 AI 恐慌；落点保持在家庭可操作。",
        "track_id": "education-yowow",
        "platform_id": "xiaohongshu",
        "positioning_id": "expert"
      },
      {
        "hotspot_id": "hs-20260612-216",
        "recommendation": "maybe",
        "forced_flag": false,
        "skip_reason": null,
        "bridge_paths": [
          {
            "path_id": "p1",
            "phenomenon": "Atlantic 撰文：『无屏玩具』营销正在收割家长的屏幕内疚，买无屏产品成了赎罪券。",
            "real_problem": "表面是消费选择，暴露的现实是：家长在为『减掉屏幕』付费，却没人为『加上什么』负责——孩子拿到无屏玩具后的输入质量，营销商不管，家长也没想。",
            "track_relation": "超然一层看：屏幕的对立面不是『无屏』，是『高质量的替代输入』——为减法买单买不来成长，供给侧才是真战场。",
            "product_value_support": "三个问题替代剁手：这玩具孩子能玩出几种花样？需要大人参与吗？玩完孩子会主动说什么？——答案决定它是输入还是摆设。",
            "platform_expression": "小红书图文：点破内疚营销，给无屏产品三问。",
            "naturalness_note": "大报观点+屏幕焦虑+供给视角，与主张同构。"
          },
          {
            "path_id": "p2",
            "phenomenon": "无屏玩具溢价高。",
            "real_problem": "为标签付费。",
            "track_relation": "看输入不看标签。",
            "product_value_support": "选购清单。",
            "platform_expression": "清单。",
            "naturalness_note": "次选。"
          },
          {
            "path_id": "p3",
            "phenomenon": "家长内疚被定价。",
            "real_problem": "情绪营销识别。",
            "track_relation": "识别『焦虑税』。",
            "product_value_support": "三种话术拆解。",
            "platform_expression": "拆解文。",
            "naturalness_note": "可用。"
          }
        ],
        "chosen_path_id": "p1",
        "content": {
          "topic": "『无屏』不是答案：你在为减法付费，孩子缺的是加法",
          "title": "花大几百买『无屏玩具』赎罪之前，先回答这三个问题💸",
          "body_or_script": "看到一篇挺扎心的文章：『无屏玩具』的营销，做的就是家长内疚的生意——你越愧疚让娃看屏幕，越愿意为『无屏』两个字掏钱，仿佛买了就赎罪了。\n\n但冷静想想：**你付费买的是『减掉屏幕』，可孩子需要的是『加上什么』**。无屏玩具买回家吃灰的还少吗？\n\n屏幕的对立面从来不是无屏，是更高质量的输入。\n\n下次剁手前先过三问👇\n1️⃣ 这东西孩子能玩出几种花样？（一种玩法的，三天弃）\n2️⃣ 需要大人参与吗？（需要的话，你有时间吗？说实话）\n3️⃣ 玩完孩子会主动跟你说什么？（说不出来的，是摆设不是输入）\n\n三问全过再买；过不了，省下的钱带娃下楼疯一小时，效果更好💪\n\n你买过最值/最坑的『无屏玩具』是什么？评论区聊聊👇"
        },
        "external_terms_check": true,
        "risk_note": "不点名具体品牌；别把无屏玩具一棍子打死，落点在三问筛选。",
        "track_id": "education-yowow",
        "platform_id": "xiaohongshu",
        "positioning_id": "expert"
      },
      {
        "hotspot_id": "hs-20260612-209",
        "recommendation": "maybe",
        "forced_flag": false,
        "skip_reason": null,
        "bridge_paths": [
          {
            "path_id": "p1",
            "phenomenon": "《低智商犯罪》热度破万：案件全是低级错误和偶然，按『聪明人犯罪』模板推理的观众全程翻车。",
            "real_problem": "表面在笑罪犯蠢，暴露的现实是：翻车的是观众自己的思维定势——我们太习惯按模板理解世界，而真实世界专出『不按模板来』的题。",
            "track_relation": "超然一层看：识别『对方可能很蠢、事情可能很偶然』恰恰是高级判断——骗局之所以得手，常因为受害者把骗子想得太聪明、把流程想得太合理。",
            "product_value_support": "给孩子的反套路练习：看新闻或故事时多问一句『还有没有更笨的解释？』——奥卡姆剃刀的儿童版，专治想太多和被带节奏。",
            "platform_expression": "小红书图文：用追剧翻车体验开场，落到信息判断练习。",
            "naturalness_note": "爆款剧+判断力，新颖角度。"
          },
          {
            "path_id": "p2",
            "phenomenon": "黑色幽默全家围观。",
            "real_problem": "适龄边界模糊。",
            "track_relation": "和孩子怎么聊犯罪题材。",
            "product_value_support": "分龄讨论法。",
            "platform_expression": "指南。",
            "naturalness_note": "次选。"
          },
          {
            "path_id": "p3",
            "phenomenon": "反转设计精巧。",
            "real_problem": "编剧思维可学。",
            "track_relation": "预测-验证游戏。",
            "product_value_support": "追剧互动法。",
            "platform_expression": "玩法。",
            "naturalness_note": "可用。"
          }
        ],
        "chosen_path_id": "p1",
        "content": {
          "topic": "全程被反转打脸后我悟了：会怀疑『更笨的解释』才是高级判断",
          "title": "追《低智商犯罪》被打脸 N 次之后，我给娃加了一道思维题🕵️",
          "body_or_script": "《低智商犯罪》热度破万，我也熬夜追完了。最大感受不是好笑，是羞愧——**每个案子我都按『高智商犯罪』的套路猜，每次都翻车**。\n\n后来想明白了：剧在嘲讽的不是罪犯，是观众的思维定势。我们默认对手很聪明、计划很缜密、动机很复杂——但真实世界里，大量事情的真相是低级错误加偶然。\n\n这恰好是骗局得手的原理：受害者把骗子想得太合理了。\n\n给孩子（和自己）的反套路练习👇\n看到任何离奇的事，多问一句：**『有没有更笨的解释？』**\n快递丢了先想想是不是放错楼，再想是不是被偷；同学『针对我』，先想想他是不是根本没注意到你。\n\n不把世界想得太精密，是判断力的起点💪\n\n你最近一次『想太多』是什么事？评论区聊聊👇"
        },
        "external_terms_check": true,
        "risk_note": "犯罪题材注意适龄表述：案例替换成生活场景，不复述剧中犯罪细节。",
        "track_id": "education-yowow",
        "platform_id": "xiaohongshu",
        "positioning_id": "expert"
      },
      {
        "hotspot_id": "hs-20260612-207",
        "recommendation": "maybe",
        "forced_flag": false,
        "skip_reason": null,
        "bridge_paths": [
          {
            "path_id": "p1",
            "phenomenon": "《家业》李祯角色热度破亿：她用制墨手艺里练出的全套判断，扛住了家族危机。",
            "real_problem": "表面在追大女主爽线，暴露的现实是：家长都在让孩子『学东西』，但学到的能不能离开课桌去解决真问题——没人验证过。",
            "track_relation": "超然一层看：李祯值钱的不是制墨手艺，是手艺背后练出的那套东西——对材料的判断、对工序的耐心、对品质的标准——这套东西走到哪个领域都能用。",
            "product_value_support": "给家长的检验法：孩子学的每样东西，定期问一句『这个本事除了课堂，还在哪儿用过一次？』——创造一次真实使用场景，比再报一个班值钱。",
            "platform_expression": "小红书图文：借剧聊『一门手艺的可迁移部分』，给真实使用场景清单。",
            "naturalness_note": "热播剧+家长心病，桥自然。"
          },
          {
            "path_id": "p2",
            "phenomenon": "女孩扛家业引共鸣。",
            "real_problem": "女孩被低估。",
            "track_relation": "能力不分性别。",
            "product_value_support": "养女孩的底气清单。",
            "platform_expression": "观点文。",
            "naturalness_note": "次选。"
          },
          {
            "path_id": "p3",
            "phenomenon": "非遗手艺翻红。",
            "real_problem": "传统技艺现代价值。",
            "track_relation": "老手艺里的新能力。",
            "product_value_support": "带孩子体验一次非遗。",
            "platform_expression": "体验路线。",
            "naturalness_note": "可用。"
          }
        ],
        "chosen_path_id": "p1",
        "content": {
          "topic": "孩子学的东西，离开课桌还能用吗？《家业》给了一个检验法",
          "title": "追《家业》上头之余，我把李祯的『本事』拆了拆，建议家长都看看🖋️",
          "body_or_script": "《家业》里李祯凭制墨手艺重振家族，角色热度破亿。很多人看的是大女主爽线，我看到的是另一件事：\n\n**她值钱的不是手艺本身，是手艺背后练出来的判断**——对材料的挑剔、对工序的耐心、对品质的死磕。墨庄塌了，这套东西没塌，走到哪儿都能重新开始。\n\n反观我们给孩子报的班：钢琴、编程、画画……学了很多『手艺』，但有没有人验证过——**离开课桌，它们在真实世界用过一次吗？**\n\n一个简单的检验法👇\n每学期问孩子一次：『你学的这个本事，除了上课，还在哪儿真用过？』\n答不上来，就帮他创造一次：学画的给家里设计春联，学编程的给班级做个值日表生成器。\n\n用出去一次，胜过再报一个班💪\n\n你家孩子的本事在课堂外用过吗？评论区聊聊👇"
        },
        "external_terms_check": true,
        "risk_note": "借剧说理，别剧透关键情节；不贬低兴趣班，落点在『创造使用场景』。",
        "track_id": "education-yowow",
        "platform_id": "xiaohongshu",
        "positioning_id": "expert"
      },
      {
        "hotspot_id": "hs-20260612-214",
        "recommendation": "maybe",
        "forced_flag": false,
        "skip_reason": null,
        "bridge_paths": [
          {
            "path_id": "p1",
            "phenomenon": "『抓得紧』派和『放得开』派又开吵，双方都举着『为孩子好』。",
            "real_problem": "表面是路线之争，暴露的现实是：两派在用同一个词说两个目标——一个优化短期成绩，一个优化长期状态，目标函数不同，吵一万年也吵不出对错。",
            "track_relation": "超然一层看：真正的问题不是选哪派，是家长有没有想清楚自己到底在优化什么——以及这个目标孩子知不知道、同不同意。",
            "product_value_support": "把站队问题换成对齐问题：全家一起写下『我们家最在乎的三件事』，所有报班和取舍都拿这三条过一遍——路线自然就清楚了。",
            "platform_expression": "小红书图文：点破目标函数混淆，给家庭对齐三步。",
            "naturalness_note": "常青争议+独特拆法，争议大需收口。"
          },
          {
            "path_id": "p2",
            "phenomenon": "两派互贴标签。",
            "real_problem": "中间派最内耗。",
            "track_relation": "不站队的第三种活法。",
            "product_value_support": "摇摆家长自救。",
            "platform_expression": "观点。",
            "naturalness_note": "次选。"
          },
          {
            "path_id": "p3",
            "phenomenon": "同伴压力裹挟。",
            "real_problem": "别人家孩子绑架决策。",
            "track_relation": "回到自家坐标系。",
            "product_value_support": "三个锚定问题。",
            "platform_expression": "清单。",
            "naturalness_note": "可用。"
          }
        ],
        "chosen_path_id": "p1",
        "content": {
          "topic": "『抓得紧』和『放得开』吵不出对错，因为它们优化的不是同一个东西",
          "title": "吵了十年的『抓得紧vs放得开』，我用一个词劝和了身边两派家长⚖️",
          "body_or_script": "『抓得紧』的家长说放养是误娃，『放得开』的家长说高压摧残童年——这架吵了十年没停过。\n\n但你发现没有：**两边都说『为孩子好』，可他们说的根本不是同一个『好』**。一派在优化短期可见的成绩，一派在优化长期的状态和能力。目标不同，当然谁也说服不了谁。\n\n所以问题从来不是『选哪派』，而是：**你想清楚自己在优化什么了吗？孩子知道吗？**\n\n我们家的做法👇\n全家开一次会，每人写下『我们最在乎的三件事』，合并成家庭版。之后所有决定——报不报班、退不退赛、管不管成绩——都拿这三条过一遍。\n\n写下来那一刻你会发现：路线之争消失了，因为你有了自己的坐标系💪\n\n你家最在乎的三件事是什么？评论区聊聊👇"
        },
        "external_terms_check": true,
        "risk_note": "争议大：通篇不贬低任何一派；发布前交博士加平衡收口。",
        "track_id": "education-yowow",
        "platform_id": "xiaohongshu",
        "positioning_id": "expert"
      },
      {
        "hotspot_id": "hs-20260612-210",
        "recommendation": "maybe",
        "forced_flag": false,
        "skip_reason": null,
        "bridge_paths": [
          {
            "path_id": "p1",
            "phenomenon": "《凡人修仙传》年番 6·13 开播：韩立从个人修炼卷入大军压境的战争棋局。",
            "real_problem": "表面是家长担心孩子沉迷爽番，暴露的现实是：孩子真正上头的不是打斗，是『普通人靠谨慎和复盘在复杂世界活下来』的叙事——这个内核家长从没接住过。",
            "track_relation": "超然一层看：与其抢遥控器，不如借角色聊真东西——韩立每次活下来靠的是评估风险、留后手、不贪快，这套东西比任何说教都容易进孩子脑子。",
            "product_value_support": "追番变素材：和孩子聊『韩立这步为什么先撤？』『换你怎么办？』——把爽点翻译成决策讨论，孩子的最爱就成了你的教具。",
            "platform_expression": "小红书图文：『别抢遥控器，借力打力』的角度给追番家长。",
            "naturalness_note": "国漫顶流+沉迷焦虑反打，角度新。"
          },
          {
            "path_id": "p2",
            "phenomenon": "年番定档引爆书粉。",
            "real_problem": "长篇叙事的耐心。",
            "track_relation": "追长篇也是深度练习。",
            "product_value_support": "和短视频对照。",
            "platform_expression": "观点。",
            "naturalness_note": "次选。"
          },
          {
            "path_id": "p3",
            "phenomenon": "凡人流逆袭叙事。",
            "real_problem": "普通孩子代入感强。",
            "track_relation": "努力之外的谨慎与复盘。",
            "product_value_support": "三个可聊问题。",
            "platform_expression": "清单。",
            "naturalness_note": "可用。"
          }
        ],
        "chosen_path_id": "p1",
        "content": {
          "topic": "孩子爱看凡人修仙？别抢遥控器，那里面有他最听得进的道理",
          "title": "儿子追《凡人修仙传》我没拦，还陪他看——这是我的私心🍃",
          "body_or_script": "《凡人修仙传》年番明天开播，家里小学生已经倒计时了。很多家长问我拦不拦。\n\n我的答案是：不拦，陪着看。私心在这👇\n\n孩子上头的从来不是打斗，是韩立这个『普通人』——没天赋没背景，靠谨慎、复盘、不贪快，在大人物的棋局里活下来。**这套生存逻辑，是孩子最容易代入、也最听得进的版本**。\n\n你讲一百遍『做事要留后手』，不如问一句：『韩立刚才为什么先撤？换你怎么办？』\n\n陪看三问（亲测有效）：\n1️⃣ 他这步在防什么？\n2️⃣ 如果失败他的后手是什么？\n3️⃣ 你在学校遇到过类似的局吗？\n\n孩子的最爱可以是你的教具，前提是你愿意蹲下来一起看💪\n\n你家娃在追什么番？评论区聊聊👇"
        },
        "external_terms_check": true,
        "risk_note": "不美化沉迷：陪看≠放任时长，文中保持时间规则前提。",
        "track_id": "education-yowow",
        "platform_id": "xiaohongshu",
        "positioning_id": "expert"
      },
      {
        "hotspot_id": "hs-20260612-201",
        "recommendation": "maybe",
        "forced_flag": false,
        "skip_reason": null,
        "bridge_paths": [
          {
            "path_id": "p1",
            "phenomenon": "海淀 6·11 电脑派位，家长彻夜研究概率组合，把入学变成资源配置推演。",
            "real_problem": "表面在拼信息和房产，暴露的现实是：这是很多家庭第一次直面『没有标准答案、结果不可控』的决策——而大人和孩子都没练过怎么跟不确定性相处。",
            "track_relation": "超然一层看：派位抽中与否无法控制，但『怎么做不确定决策』可以练——列选项、想后手、接受结果，这套动作才是能留给孩子的。",
            "product_value_support": "把派位变成家庭决策课：让孩子旁听一次全家讨论——我们有哪些选择？最坏结果是什么？后手是什么？抽完签一起复盘。",
            "platform_expression": "小红书图文：用『彻夜算概率』共情开场，给不确定性决策三步。",
            "naturalness_note": "政策热点转能力视角，桥成立但要快收。"
          },
          {
            "path_id": "p2",
            "phenomenon": "学区房价值波动。",
            "real_problem": "资产焦虑传导给孩子。",
            "track_relation": "别让孩子接住大人的焦虑。",
            "product_value_support": "跟孩子怎么谈派位。",
            "platform_expression": "对话模板。",
            "naturalness_note": "次选。"
          },
          {
            "path_id": "p3",
            "phenomenon": "非京籍家庭更难。",
            "real_problem": "规则复杂度极高。",
            "track_relation": "读懂规则本身是能力。",
            "product_value_support": "带孩子拆一次规则文本。",
            "platform_expression": "实操。",
            "naturalness_note": "可用。"
          }
        ],
        "chosen_path_id": "p1",
        "content": {
          "topic": "派位抽不中没法控制，但『跟不确定性相处』可以练",
          "title": "海淀派位夜，全家算概率到凌晨…其实最该上课的不是孩子🎲",
          "body_or_script": "昨晚海淀派位确认，家长群里全是概率表和志愿组合。\n\n说真的，看着大家彻夜推演，我突然意识到：**这是很多家庭第一次集体直面『没有标准答案』的决策**——做了所有准备，结果还是要交给随机。\n\n大人都慌，因为我们这代人也没练过。但这恰恰是孩子未来天天要面对的事。\n\n把派位变成全家的『不确定性第一课』👇\n1️⃣ 让孩子旁听决策：我们有哪些选项？各自好在哪？\n2️⃣ 提前想最坏情况：没抽中怎么办？后手是什么？\n3️⃣ 出结果后复盘：我们控制了什么、没控制什么、下次怎么做？\n\n抽签结果留给运气，决策能力留给孩子。这才是派位夜真正值钱的部分💪\n\n你家是怎么跟孩子解释『没抽中』的？评论区聊聊👇"
        },
        "external_terms_check": true,
        "risk_note": "不评价政策本身、不渲染学区房焦虑；落点保持在家庭决策练习。",
        "track_id": "education-yowow",
        "platform_id": "xiaohongshu",
        "positioning_id": "expert"
      }
    ],
    "also_ran": [],
    "skipped": [
      {
        "hotspot_id": "hs-20260612-202",
        "track_id": "education-yowow",
        "platform_id": "xiaohongshu",
        "positioning_id": "expert",
        "recommendation": "skip",
        "forced_flag": true,
        "skip_reason": "托管服务信息，家长焦虑真实但落点在公共服务供给，接到孩子能力培养要绕一大圈。",
        "bridge_paths": [],
        "chosen_path_id": null,
        "content": null,
        "external_terms_check": true
      },
      {
        "hotspot_id": "hs-20260612-203",
        "track_id": "education-yowow",
        "platform_id": "xiaohongshu",
        "positioning_id": "expert",
        "recommendation": "skip",
        "forced_flag": true,
        "skip_reason": "细节少、热度低，属于局部通知类，不足以支撑深度剖析。",
        "bridge_paths": [],
        "chosen_path_id": null,
        "content": null,
        "external_terms_check": true
      },
      {
        "hotspot_id": "hs-20260612-206",
        "track_id": "education-yowow",
        "platform_id": "xiaohongshu",
        "positioning_id": "expert",
        "recommendation": "skip",
        "forced_flag": true,
        "skip_reason": "官方晚会内容散、二创少，蹭官方策划节目容易空泛，没有自然的能力落点。",
        "bridge_paths": [],
        "chosen_path_id": null,
        "content": null,
        "external_terms_check": true
      },
      {
        "hotspot_id": "hs-20260612-208",
        "track_id": "education-yowow",
        "platform_id": "xiaohongshu",
        "positioning_id": "expert",
        "recommendation": "skip",
        "forced_flag": true,
        "skip_reason": "长期训练叙事可接但戏曲行业离小学家长日常远，同类影视已有更自然的（家业/低智商犯罪），避免扎堆硬蹭。",
        "bridge_paths": [],
        "chosen_path_id": null,
        "content": null,
        "external_terms_check": true
      },
      {
        "hotspot_id": "hs-20260612-213",
        "track_id": "education-yowow",
        "platform_id": "xiaohongshu",
        "positioning_id": "expert",
        "recommendation": "skip",
        "forced_flag": true,
        "skip_reason": "专注力是真问题但没有新事件由头，属于常青选题不是今日热点；建议进选题库择日配事件再做。",
        "bridge_paths": [],
        "chosen_path_id": null,
        "content": null,
        "external_terms_check": true
      },
      {
        "hotspot_id": "hs-20260612-215",
        "track_id": "education-yowow",
        "platform_id": "xiaohongshu",
        "positioning_id": "expert",
        "recommendation": "skip",
        "forced_flag": true,
        "skip_reason": "观点扎实但语境偏欧美职场，接到中国小学家长要先做一层转译，今天有更直接的 AI 教育热点（AI 志愿填报），不必绕。",
        "bridge_paths": [],
        "chosen_path_id": null,
        "content": null,
        "external_terms_check": true
      }
    ]
  },
  "meta": {
    "hs-20260612-201": {
      "oneLiner": "海淀幼升小 6·11 电脑派位确认，家长彻夜研究概率",
      "reason": "家长在算派位概率，真正暴露的是：全家第一次被迫做『没有标准答案的不确定性决策』——这恰是最该带孩子一起练的题。"
    },
    "hs-20260612-202": {
      "oneLiner": "上海暑托班开抢：名额、安全、接送全压在家长身上",
      "reason": "托管服务信息，家长焦虑真实但落点在公共服务供给，接到孩子能力培养要绕一大圈。"
    },
    "hs-20260612-203": {
      "oneLiner": "高考考点占用致中小学停课，孩子居家谁来管",
      "reason": "细节少、热度低，属于局部通知类，不足以支撑深度剖析。"
    },
    "hs-20260612-204": {
      "oneLiner": "高考后 AI 志愿填报爆发：3000 所高校的信息突围战",
      "reason": "大家在围观 AI 填志愿的神奇，真正暴露的是：工具能给方案，但目标和取舍只能自己定——『会用 AI 做路径决策』正是孩子这代人的必修课，从小学就能开始练。"
    },
    "hs-20260612-205": {
      "oneLiner": "《爸爸当家5》乐悠安抚妹妹包揽家务，5000万播放引爆『被迫懂事』之争",
      "reason": "全网吵『被迫懂事』还是『有责任感』，真正暴露的是：大家分不清牺牲式懂事和被需要出来的能力——这条界线恰好是家长最该看懂的。"
    },
    "hs-20260612-206": {
      "oneLiner": "央视六一晚会：AI 伙伴、劳动、戏曲、运动装进同一套成长叙事",
      "reason": "官方晚会内容散、二创少，蹭官方策划节目容易空泛，没有自然的能力落点。"
    },
    "hs-20260612-207": {
      "oneLiner": "《家业》李祯凭制墨技艺重振家族：一门手艺如何撑起一场危机",
      "reason": "大家在追李祯爽线，真正值钱的是结构：她不是『会一门手艺』，是把制墨里练出的判断力迁到了家族危机里——『学的东西能不能用出去』正是家长的心病。"
    },
    "hs-20260612-208": {
      "oneLiner": "《主角》：秦腔演员的长期训练与舞台成长引发成才讨论",
      "reason": "长期训练叙事可接但戏曲行业离小学家长日常远，同类影视已有更自然的（家业/低智商犯罪），避免扎堆硬蹭。"
    },
    "hs-20260612-209": {
      "oneLiner": "《低智商犯罪》爱奇艺热度破万：荒诞案件专治『聪明人套路』",
      "reason": "观众笑罪犯蠢，真正暴露的是自己的思维定势：按『聪明人模板』推理全翻车——给孩子的信息判断课就藏在这个反转里。注意犯罪题材适龄表述。"
    },
    "hs-20260612-210": {
      "oneLiner": "《凡人修仙传》年番定档：韩立从个人修炼卷入大战局",
      "reason": "家长怕孩子沉迷，真正可借的是结构：韩立从个人努力的小逻辑升级到大系统判断——正好把『爽文』翻译成『复杂环境里怎么做决定』。"
    },
    "hs-20260612-212": {
      "oneLiner": "手机短视频游戏沉迷：从『堵不住』到家庭规则重建",
      "reason": "全家都在打『屏幕争夺战』且全线溃败，真正暴露的是：堵的本质是供给问题——孩子的高质量输入没人提供，屏幕才不可替代。暑假前正是讲透这件事的时点。"
    },
    "hs-20260612-213": {
      "oneLiner": "专注力告急：AI 时代最稀缺的是长时间不被打断",
      "reason": "专注力是真问题但没有新事件由头，属于常青选题不是今日热点；建议进选题库择日配事件再做。"
    },
    "hs-20260612-214": {
      "oneLiner": "抓得紧还是放得开？吵的其实是两个目标函数",
      "reason": "两派吵『为孩子好』，真正暴露的是：他们在用同一个词说两个目标函数——短期成绩和长期能力。点破这个混淆能让两派都坐下来。争议大，发布前交博士收口。"
    },
    "hs-20260612-215": {
      "oneLiner": "FT：雇主开始自己填补 AI 教育缺口",
      "reason": "观点扎实但语境偏欧美职场，接到中国小学家长要先做一层转译，今天有更直接的 AI 教育热点（AI 志愿填报），不必绕。"
    },
    "hs-20260612-216": {
      "oneLiner": "Atlantic：屏幕越泛滥，『无屏玩具』越能贩卖家长内疚",
      "reason": "家长为『无屏』付费买安心，真正暴露的是：大家在为减法付费，却没人为『输入质量』负责——屏幕的问题从来不是屏幕本身，是替代供给太差。"
    }
  },
  "mode": "live",
  "notice": "今日内容已由人工跑批安装；如需修改，请按 RUNBOOK 重新跑批。",
  "date": "2026-06-12",
  "generated_at": "2026-06-11T15:14:53"
}
